spd_eda/__init__.py
spd_eda/athena_tools/__init__.py
spd_eda/athena_tools/athena_column.py
spd_eda/athena_tools/athena_table.py
spd_eda/athena_tools/utils.py
spd_eda/dataframe_structure/__init__.py
spd_eda/dataframe_structure/dataframe_structure.py
spd_eda/eda_tools/__init__.py
spd_eda/eda_tools/eda.py
spd_eda/excel_tools/__init__.py
spd_eda/excel_tools/excel_output.py
spd_eda/hh_batch/__init__.py
spd_eda/hh_batch/api_batch.py
spd_eda/hh_batch/portfolio_analysis.py
spd_eda/hh_batch/report.py
spd_eda/hh_batch/config/__init__.py
spd_eda/hh_batch/config/base_report_config.csv
spd_eda/hh_batch/config/batch_column_config.csv
spd_eda/hh_batch/config/batch_data_dictionary.csv
spd_eda/hh_batch/config/config.py
spd_eda/hh_batch/config/report_translation_tables.xlsx
spd_eda/hh_batch/tests/__init__.py
spd_eda/hh_batch/tests/scratch.py
spd_eda/hh_batch/utils/__init__.py
spd_eda/hh_batch/utils/binning_utils.py
spd_eda/hh_batch/utils/chart_utils.py
spd_eda/hh_batch/utils/excel_utils.py
spd_eda/hh_batch/utils/stat_utils.py
spd_eda/hh_peril_analysis/__init__.py
spd_eda/hh_peril_analysis/peril_analysis.py
spd_eda/modeling/__init__.py
spd_eda/modeling/utils/__init__.py
spd_eda/modeling/utils/binning_utils.py
spd_eda/pa/__init__.py
spd_eda/pa/analysis.py
spd_eda/pa/analysis_summary.py
spd_eda/pa/config.py
spd_eda/pa/connection.py
spd_eda/pa/datasource.py
spd_eda/pa/dataview.py
spd_eda/pa/dataview_eda.py
spd_eda/pa/pa_stats.py
spd_eda/pa/plinko.py
spd_eda/sql_tools/__init__.py
spd_eda/sql_tools/connection.py
spd_eda/sql_tools/sql_table.py
spd_eda/sql_tools/utils.py
spd_eda-0.2.0.dist-info/LICENSE
spd_eda-0.2.0.dist-info/METADATA
spd_eda-0.2.0.dist-info/WHEEL
spd_eda-0.2.0.dist-info/top_level.txt
spd_eda-0.2.0.dist-info/RECORD
