Metadata-Version: 2.1
Name: spd-eda
Version: 0.2.0
Summary: initial testing
Author-email: sdooley <author@example.com>
Classifier: Programming Language :: Python :: 3
Classifier: License :: OSI Approved :: MIT License
Classifier: Operating System :: OS Independent
Requires-Python: >=3.8
License-File: LICENSE
Requires-Dist: pandas >=1.5
Requires-Dist: xlsxwriter >=3.0.3
Requires-Dist: pyodbc >=4.0.34
Requires-Dist: seaborn >=0.12.0
Requires-Dist: scipy >=1.9.1
Requires-Dist: awswrangler >=2.16.1
